slam_dataset_sdk/__init__.py
slam_dataset_sdk/config.py
slam_dataset_sdk/datasets_iterator.py
slam_dataset_sdk/deskew.py
slam_dataset_sdk/mapping.py
slam_dataset_sdk/metrics.py
slam_dataset_sdk/odometry.py
slam_dataset_sdk/pipeline.py
slam_dataset_sdk/preprocess.py
slam_dataset_sdk/voxelization.py
slam_dataset_sdk/config/default.yaml
slam_dataset_sdk/datasets/__init__.py
slam_dataset_sdk/datasets/apollo.py
slam_dataset_sdk/datasets/boreas.py
slam_dataset_sdk/datasets/generic.py
slam_dataset_sdk/datasets/kitti.py
slam_dataset_sdk/datasets/kitti_raw.py
slam_dataset_sdk/datasets/mulran.py
slam_dataset_sdk/datasets/mydataset.py
slam_dataset_sdk/datasets/ncd.py
slam_dataset_sdk/datasets/nclt.py
slam_dataset_sdk/datasets/nuscenes.py
slam_dataset_sdk/datasets/oxford.py
slam_dataset_sdk/datasets/paris_luco.py
slam_dataset_sdk/datasets/rosbag.py
slam_dataset_sdk/datasets/rosbag2.py
slam_dataset_sdk/tools/__init__.py
slam_dataset_sdk/tools/cmd.py
slam_dataset_sdk/tools/pipeline_results.py
slam_dataset_sdk/tools/progress_bar.py
slam_dataset_sdk/tools/visualizer.py
slam_dataset_sdk/tools/oxford_sdk/__init__.py
slam_dataset_sdk/tools/oxford_sdk/interpolate_poses.py
slam_dataset_sdk/tools/oxford_sdk/transform.py
slam_dataset_sdk/tools/oxford_sdk/velodyne.py
slam_dataset_sdk/tools/oxford_sdk/extrinsics/__init__.py
slam_dataset_sdk-0.0.2.dist-info/LICENSE
slam_dataset_sdk-0.0.2.dist-info/METADATA
slam_dataset_sdk-0.0.2.dist-info/WHEEL
slam_dataset_sdk-0.0.2.dist-info/entry_points.txt
slam_dataset_sdk-0.0.2.dist-info/top_level.txt
slam_dataset_sdk-0.0.2.dist-info/RECORD
