Metadata-Version: 2.1
Name: slam-dataset-sdk
Version: 0.0.2
Summary: Simple 3D LiDAR-Odometry dataset loading pipeline
Home-page: https://github.com/pranayspeed/slam_dataset_iterator
Author: Pranay Meshram
Author-email: pranaywa@buffalo.edu
License: MIT
Keywords: SLAM,LiDAR,Odometry,Localization
Classifier: Operating System :: Unix
Classifier: Operating System :: MacOS
Classifier: Operating System :: Microsoft :: Windows
Classifier: Programming Language :: C++
Classifier: Programming Language :: Python :: 3
Classifier: Programming Language :: Python :: 3.7
Classifier: Programming Language :: Python :: 3.8
Classifier: Programming Language :: Python :: 3.9
Classifier: Programming Language :: Python :: 3.10
Classifier: Programming Language :: Python :: 3.11
Classifier: Intended Audience :: Developers
Classifier: Intended Audience :: Education
Classifier: Intended Audience :: Other Audience
Classifier: Intended Audience :: Science/Research
Classifier: License :: OSI Approved :: MIT License
License-File: LICENSE
Requires-Dist: PyYAML
Requires-Dist: easydict
Requires-Dist: natsort
Requires-Dist: numpy
Requires-Dist: plyfile
Requires-Dist: pyquaternion
Requires-Dist: rich
Requires-Dist: tqdm
Requires-Dist: typer[all] (>=0.6.0)
Provides-Extra: all
Requires-Dist: open3d (>=0.13) ; extra == 'all'
Requires-Dist: pyntcloud ; extra == 'all'
Requires-Dist: trimesh ; extra == 'all'
Provides-Extra: visualizer
Requires-Dist: open3d (>=0.13) ; extra == 'visualizer'
